orb/__init__.py
orb/_version.py
orb/decorators.py
orb/errors.py
orb/settings.py
orb/core/__init__.py
orb/core/collection.py
orb/core/collector.py
orb/core/column.py
orb/core/connection.py
orb/core/context.py
orb/core/database.py
orb/core/events.py
orb/core/index.py
orb/core/metamodel.py
orb/core/model.py
orb/core/modelmixin.py
orb/core/pipe.py
orb/core/query.py
orb/core/reverselookup.py
orb/core/schema.py
orb/core/search.py
orb/core/security.py
orb/core/syntax.py
orb/core/system.py
orb/core/transactions.py
orb/core/column_types/__init__.py
orb/core/column_types/boolean.py
orb/core/column_types/data.py
orb/core/column_types/dtime.py
orb/core/column_types/ids.py
orb/core/column_types/join.py
orb/core/column_types/numeric.py
orb/core/column_types/reference.py
orb/core/column_types/shortcut.py
orb/core/column_types/string.py
orb/core/connection_types/__init__.py
orb/core/connection_types/sql/__init__.py
orb/core/connection_types/sql/sqlconnection.py
orb/core/connection_types/sql/sqlstatement.py
orb/core/connection_types/sql/mysql/__init__.py
orb/core/connection_types/sql/mysql/mysqlconnection.py
orb/core/connection_types/sql/mysql/statements/__init__.py
orb/core/connection_types/sql/mysql/statements/add_column.py
orb/core/connection_types/sql/mysql/statements/alter.py
orb/core/connection_types/sql/mysql/statements/create.py
orb/core/connection_types/sql/mysql/statements/create_index.py
orb/core/connection_types/sql/mysql/statements/create_namespace.py
orb/core/connection_types/sql/mysql/statements/delete.py
orb/core/connection_types/sql/mysql/statements/enable_internals.py
orb/core/connection_types/sql/mysql/statements/insert.py
orb/core/connection_types/sql/mysql/statements/schema_info.py
orb/core/connection_types/sql/mysql/statements/select.py
orb/core/connection_types/sql/mysql/statements/select_count.py
orb/core/connection_types/sql/mysql/statements/update.py
orb_api-2016.1.50.dist-info/DESCRIPTION.rst
orb_api-2016.1.50.dist-info/METADATA
orb_api-2016.1.50.dist-info/metadata.json
orb_api-2016.1.50.dist-info/RECORD
orb_api-2016.1.50.dist-info/top_level.txt
orb_api-2016.1.50.dist-info/WHEEL
