Metadata-Version: 2.0
Name: orb-api
Version: 2016.1.50
Summary: Database ORM and API builder.
Home-page: https://github.com/orb-framework/orb
Author: Eric Hulser
Author-email: eric.hulser@gmail.com
License: MIT
Platform: UNKNOWN
Requires-Dist: projex (>=2015.0.12)
Requires-Dist: inflection
Requires-Dist: pycrypto
Requires-Dist: pyparsing
Requires-Dist: pyyaml
Requires-Dist: pytz
